Metadata-Version: 2.1
Name: websocket-client
Version: 1.6.4
Summary: WebSocket client for Python with low level API options
Home-page: https://github.com/websocket-client/websocket-client.git
Author: liris
Author-email: liris.pp@gmail.com
Maintainer: engn33r
Maintainer-email: websocket.client@proton.me
License: Apache-2.0
Download-URL: https://github.com/websocket-client/websocket-client/releases
Project-URL: Documentation, https://websocket-client.readthedocs.io/
Project-URL: Source, https://github.com/websocket-client/websocket-client/
Keywords: websockets client
Platform: UNKNOWN
Classifier: Development Status :: 4 - Beta
Classifier: License :: OSI Approved :: Apache Software License
Classifier: Programming Language :: Python :: 3
Classifier: Programming Language :: Python :: 3.8
Classifier: Programming Language :: Python :: 3.9
Classifier: Programming Language :: Python :: 3.10
Classifier: Programming Language :: Python :: 3.11
Classifier: Programming Language :: Python :: 3.12
Classifier: Operating System :: MacOS :: MacOS X
Classifier: Operating System :: POSIX
Classifier: Operating System :: Microsoft :: Windows
Classifier: Topic :: Internet
Classifier: Topic :: Software Development :: Libraries :: Python Modules
Classifier: Intended Audience :: Developers
Requires-Python: >=3.8
Provides-Extra: docs
Provides-Extra: optional
Provides-Extra: test
License-File: LICENSE
